MANIFEST.in
README.md
README.rst
distribute_setup.py
setup.py
teena/__init__.py
teena/cached_property.py
teena/capture.py
teena/error.py
teena/fdutils.py
teena/pipe.py
teena/tee.py
teena/thread_loop.py
teena.egg-info/PKG-INFO
teena.egg-info/SOURCES.txt
teena.egg-info/dependency_links.txt
teena.egg-info/requires.txt
teena.egg-info/top_level.txt
test/test_cached_property.py
test/test_capture.py
test/test_error.py
test/test_pipe.py
test/test_tee.py
test/test_thread_loop.py