Metadata-Version: 1.0
Name: teena
Version: 0.0.2
Summary: Python ports of useful syscalls, using asynchronous I/O.
Home-page: http://github.com/zacharyvoase/teena
Author: Zachary Voase
Author-email: z@zacharyvoase.com
License: UNKNOWN
Platform: UNKNOWN
